sabcom/__init__.py
sabcom/__main__.py
sabcom/agent.py
sabcom/differential_equation_model.py
sabcom/environment.py
sabcom/estimation.py
sabcom/helpers.py
sabcom/runner.py
sabcom/updater.py
tests/__init__.py
tests/test_application.py
sabcom-0.44a0.dist-info/LICENSE
sabcom-0.44a0.dist-info/METADATA
sabcom-0.44a0.dist-info/WHEEL
sabcom-0.44a0.dist-info/entry_points.txt
sabcom-0.44a0.dist-info/top_level.txt
sabcom-0.44a0.dist-info/RECORD
