Metadata-Version: 2.1
Name: sabcom
Version: 0.44a0
Summary: SABCOM is an open source, easy-to-use, social network, agent-based, model that can be used to simulate the effects of different lockdown policy measures on the spread of the Covid-19 virus in several (South African) cities.
Home-page: https://github.com/blackrhinoabm/sabcom
Author: Joeri Schasfoort
Author-email: joeri.schasfoort@uct.ac.za
License: MIT
Download-URL: https://github.com/blackrhinoabm/sabcom/archive/1.0.0.tar.gz
Platform: UNKNOWN
Classifier: License :: OSI Approved :: MIT License
Classifier: Programming Language :: Python :: 3.6
Classifier: Programming Language :: Python :: 3.7
Classifier: Programming Language :: Python :: 3.8
Requires-Python: >=3.6
Requires-Dist: joblib
Requires-Dist: SALib
Requires-Dist: click
Requires-Dist: decorator
Requires-Dist: networkx
Requires-Dist: numpy
Requires-Dist: pandas
Requires-Dist: python-dateutil
Requires-Dist: pytz
Requires-Dist: scikit-learn
Requires-Dist: scipy
Requires-Dist: sklearn
Requires-Dist: threadpoolctl
Requires-Dist: xlrd
